jvitali/BasicMath.py
jvitali/ListFunctions.py
jvitali/__init__.py
jvitali-0.0.1.dist-info/METADATA
jvitali-0.0.1.dist-info/WHEEL
jvitali-0.0.1.dist-info/top_level.txt
jvitali-0.0.1.dist-info/RECORD
