Metadata-Version: 2.1
Name: jvitali
Version: 0.0.1
Summary: Displaying my first python lib, have fun using it!
Home-page: https://github.com/JV39/jvitali
Author: Jean Vitali
Author-email: vitali.jean.03@gmail.com
License: UNKNOWN
Platform: UNKNOWN
Classifier: Programming Language :: Python :: 3
Classifier: License :: OSI Approved :: MIT License
Classifier: Operating System :: OS Independent
Requires-Python: >=3.6
